<annotation>
	<folder>Grape___Leaf_blight_Isariopsis_Leaf_Spot</folder>
	<filename>0cd6d9f4-ffa6-49a6-aa21-a7955d1bef56___FAM_L.Blight 1641.JPG</filename>
	<path>C:\Users\sanja\Desktop\Courses\Deep Learning\Proj\leafDataForBoudingBox\Grape___Leaf_blight_Isariopsis_Leaf_Spot\0cd6d9f4-ffa6-49a6-aa21-a7955d1bef56___FAM_L.Blight 1641.JPG</path>
	<source>
		<database>Unknown</database>
	</source>
	<size>
		<width>256</width>
		<height>256</height>
		<depth>3</depth>
	</size>
	<segmented>0</segmented>
	<object>
		<name>GrapeLeafBlightIsariopsis</name>
		<pose>Unspecified</pose>
		<truncated>0</truncated>
		<difficult>0</difficult>
		<bndbox>
			<xmin>70</xmin>
			<ymin>141</ymin>
			<xmax>97</xmax>
			<ymax>156</ymax>
		</bndbox>
	</object>
	<object>
		<name>GrapeLeafBlightIsariopsis</name>
		<pose>Unspecified</pose>
		<truncated>0</truncated>
		<difficult>0</difficult>
		<bndbox>
			<xmin>120</xmin>
			<ymin>83</ymin>
			<xmax>142</xmax>
			<ymax>106</ymax>
		</bndbox>
	</object>
	<object>
		<name>GrapeLeafBlightIsariopsis</name>
		<pose>Unspecified</pose>
		<truncated>0</truncated>
		<difficult>0</difficult>
		<bndbox>
			<xmin>68</xmin>
			<ymin>178</ymin>
			<xmax>90</xmax>
			<ymax>193</ymax>
		</bndbox>
	</object>
	<object>
		<name>GrapeLeafBlightIsariopsis</name>
		<pose>Unspecified</pose>
		<truncated>0</truncated>
		<difficult>0</difficult>
		<bndbox>
			<xmin>144</xmin>
			<ymin>141</ymin>
			<xmax>168</xmax>
			<ymax>163</ymax>
		</bndbox>
	</object>
	<object>
		<name>GrapeLeafBlightIsariopsis</name>
		<pose>Unspecified</pose>
		<truncated>0</truncated>
		<difficult>0</difficult>
		<bndbox>
			<xmin>24</xmin>
			<ymin>130</ymin>
			<xmax>62</xmax>
			<ymax>163</ymax>
		</bndbox>
	</object>
	<object>
		<name>GrapeLeafBlightIsariopsis</name>
		<pose>Unspecified</pose>
		<truncated>0</truncated>
		<difficult>0</difficult>
		<bndbox>
			<xmin>60</xmin>
			<ymin>71</ymin>
			<xmax>95</xmax>
			<ymax>118</ymax>
		</bndbox>
	</object>
	<object>
		<name>GrapeLeafBlightIsariopsis</name>
		<pose>Unspecified</pose>
		<truncated>0</truncated>
		<difficult>0</difficult>
		<bndbox>
			<xmin>185</xmin>
			<ymin>165</ymin>
			<xmax>197</xmax>
			<ymax>184</ymax>
		</bndbox>
	</object>
	<object>
		<name>GrapeLeafBlightIsariopsis</name>
		<pose>Unspecified</pose>
		<truncated>0</truncated>
		<difficult>0</difficult>
		<bndbox>
			<xmin>165</xmin>
			<ymin>193</ymin>
			<xmax>192</xmax>
			<ymax>213</ymax>
		</bndbox>
	</object>
	<object>
		<name>GrapeLeafBlightIsariopsis</name>
		<pose>Unspecified</pose>
		<truncated>0</truncated>
		<difficult>0</difficult>
		<bndbox>
			<xmin>108</xmin>
			<ymin>129</ymin>
			<xmax>136</xmax>
			<ymax>183</ymax>
		</bndbox>
	</object>
	<object>
		<name>GrapeLeafBlightIsariopsis</name>
		<pose>Unspecified</pose>
		<truncated>0</truncated>
		<difficult>0</difficult>
		<bndbox>
			<xmin>131</xmin>
			<ymin>12</ymin>
			<xmax>149</xmax>
			<ymax>26</ymax>
		</bndbox>
	</object>
	<object>
		<name>GrapeLeafBlightIsariopsis</name>
		<pose>Unspecified</pose>
		<truncated>0</truncated>
		<difficult>0</difficult>
		<bndbox>
			<xmin>191</xmin>
			<ymin>148</ymin>
			<xmax>207</xmax>
			<ymax>160</ymax>
		</bndbox>
	</object>
	<object>
		<name>GrapeLeafBlightIsariopsis</name>
		<pose>Unspecified</pose>
		<truncated>0</truncated>
		<difficult>0</difficult>
		<bndbox>
			<xmin>184</xmin>
			<ymin>110</ymin>
			<xmax>196</xmax>
			<ymax>123</ymax>
		</bndbox>
	</object>
</annotation>
